{
  "expenses": [
    {
      "id": "EXP-2026-0001",
      "date": "2026-01-28",
      "shipment": "8062137294",
      "bu": "060C",
      "employeeName": "นายศักดิ์ทวสลินทาพย์",
      "employeeId": "39396",
      "employeePhone": "71-5432",
      "type": "ค่าทางด่วน (Toll)",
      "payment": "Cash",
      "vendor": "-",
      "amount": 250.00,
      "receipt": "📷",
      "caRef": "CA-2026-0045",
      "status": "Approved",
      "statusState": "Success",
      "statusIcon": "sap-icon://accept"
    },
    {
      "id": "EXP-2026-0002",
      "date": "2026-01-28",
      "shipment": "8062137294",
      "bu": "060C",
      "employeeName": "นายศักดิ์ทวสลินทาพย์",
      "employeeId": "39396",
      "employeePhone": "71-5432",
      "type": "ค่าอาหาร (Meal)",
      "payment": "Cash",
      "vendor": "-",
      "amount": 150.00,
      "receipt": "-",
      "caRef": "CA-2026-0045",
      "status": "Approved",
      "statusState": "Success",
      "statusIcon": "sap-icon://accept"
    },
    {
      "id": "EXP-2026-0003",
      "date": "2026-01-28",
      "shipment": "8062137294",
      "bu": "060C",
      "employeeName": "นายศักดิ์ทวสลินทาพย์",
      "employeeId": "39396",
      "employeePhone": "71-5432",
      "type": "ค่าชั่งน้ำหนัก (Weighbridge)",
      "payment": "Cash",
      "vendor": "-",
      "amount": 100.00,
      "receipt": "📷",
      "caRef": "CA-2026-0045",
      "status": "Approved",
      "statusState": "Success",
      "statusIcon": "sap-icon://accept"
    },
    {
      "id": "EXP-2026-0004",
      "date": "2026-01-28",
      "shipment": "8062137294",
      "bu": "060C",
      "employeeName": "นายศักดิ์ทวสลินทาพย์",
      "employeeId": "39396",
      "employeePhone": "71-5432",
      "type": "ค่าค้างคืน (Overnight)",
      "payment": "Cash",
      "vendor": "-",
      "amount": 800.00,
      "receipt": "📷",
      "caRef": "CA-2026-0045",
      "status": "Rejected",
      "statusState": "Error",
      "statusIcon": "sap-icon://decline"
    },
    {
      "id": "EXP-2026-0005",
      "date": "2026-01-29",
      "shipment": "8062137301",
      "bu": "060E",
      "employeeName": "นายสมชาย แสงทอง",
      "employeeId": "40125",
      "employeePhone": "72-1180",
      "type": "ค่าทางด่วน (Toll)",
      "payment": "Cash",
      "vendor": "-",
      "amount": 180.00,
      "receipt": "📷",
      "caRef": "CA-2026-0052",
      "status": "Pending Review",
      "statusState": "Warning",
      "statusIcon": "sap-icon://pending"
    },
    {
      "id": "EXP-2026-0006",
      "date": "2026-01-29",
      "shipment": "8062137301",
      "bu": "060E",
      "employeeName": "นายสมชาย แสงทอง",
      "employeeId": "40125",
      "employeePhone": "72-1180",
      "type": "ค่าอาหาร (Meal)",
      "payment": "Cash",
      "vendor": "-",
      "amount": 120.00,
      "receipt": false,
      "caRef": "CA-2026-0052",
      "status": "Pending Review",
      "statusState": "Warning",
      "statusIcon": "sap-icon://pending"
    },
    {
      "id": "EXP-2026-0007",
      "date": "2026-01-30",
      "shipment": "8062137310",
      "bu": "060F",
      "employeeName": "นายวิชัย บุญรัตน์",
      "employeeId": "40280",
      "employeePhone": "73-4556",
      "type": "ค่าผ่านท่า (Port Fee)",
      "payment": "Cash",
      "vendor": "-",
      "amount": 500.00,
      "receipt": "📷",
      "caRef": "-",
      "status": "Draft",
      "statusState": "None",
      "statusIcon": "sap-icon://edit"
    },
    {
      "id": "EXP-2026-0009",
      "date": "2026-01-31",
      "shipment": "8062137320",
      "bu": "060C",
      "employeeName": "นายศักดิ์ทวสลินทาพย์",
      "employeeId": "39396",
      "employeePhone": "71-5432",
      "type": "ค่าทางด่วน (Toll)",
      "payment": "Cash",
      "vendor": "-",
      "amount": 200.00,
      "receipt": "📷",
      "caRef": "CA-2026-0045",
      "status": "Posted",
      "statusState": "Information",
      "statusIcon": "sap-icon://post"
    }
  ],

  "fuelRecords": [
    {
      "id": "FUEL-2026-0001",
      "date": "2026-01-28",
      "shipment": "8062137294",
      "bu": "060C",
      "fillType": "Fleet Card",
      "vehicle": "71-5432",
      "driver": "นายศักดิ์ทวสลินทาพย์",
      "station": "PTT Station บางนา",
      "fuel": "Diesel B7",
      "liters": 180.50,
      "amount": 5584.67,
      "rate": "4.1 km/L",
      "status": "Approved",
      "statusState": "Success"
    },
    {
      "id": "FUEL-2026-0002",
      "date": "2026-01-28",
      "shipment": "8062137294",
      "bu": "060C",
      "fillType": "Cash",
      "vehicle": "71-5432",
      "driver": "นายศักดิ์ทวสลินทาพย์",
      "station": "Shell สระบุรี",
      "fuel": "Diesel B7",
      "liters": 50.00,
      "amount": 1547.00,
      "rate": "4.1 km/L",
      "status": "Approved",
      "statusState": "Success"
    },
    {
      "id": "FUEL-2026-0003",
      "date": "2026-01-29",
      "shipment": "8062137301",
      "bu": "060E",
      "fillType": "Fleet Card",
      "vehicle": "72-1180",
      "driver": "นายสมชาย แสงทอง",
      "station": "PTT Station โคราช",
      "fuel": "Diesel B7",
      "liters": 220.00,
      "amount": 6806.80,
      "rate": "3.3 km/L",
      "status": "Pending Review",
       "statusState": "Warning"
    },
    {
      "id": "FUEL-2026-0004",
      "date": "2026-01-30",
      "shipment": "8062137310",
      "bu": "060F",
      "fillType": "Store Fuel",
      "vehicle": "73-4556",
      "driver": "นายวิชัย บุญรัตน์",
      "station": "คลังน้ำมัน BPK",
      "fuel": "Diesel B7",
      "liters": 300.00,
      "amount": 9282.00,
      "rate": "3.6 km/L",
       "statusState": "None",
      "status": "Draft"
    },
    {
      "id": "FUEL-2026-0005",
      "date": "2026-01-31",
      "shipment": "8062137320",
      "bu": "060C",
      "fillType": "Fleet Card",
      "vehicle": "71-5432",
      "driver": "นายศักดิ์ทวสลินทาพย์",
      "station": "Bangchak บางนา",
      "fuel": "Diesel B7",
      "liters": 195.00,
      "amount": 6033.30,
      "rate": "4.1 km/L",
      "statusState": "Information",
      "status": "Posted"
    }
  ],
   "parkingRecords": [
    {
      "id": "PRK-2026-0001",
      "shipment": "8062137294",
      "bu": "060C",
      "stage": "1",
      "place": "ลานจอด PTT ระยอง",
      "type": "ปั้มน้ำมัน",
      "start": "2026-01-28 10:30",
      "end": "2026-01-28 11:15",
      "duration": "0h 45m",
      "reason": "รอคิวส่งสินค้า",
      "amount": 50.00,
      "status": "Approved",
      "statusColor": "Success"
    },
    {
      "id": "PRK-2026-0002",
      "shipment": "8062137294",
      "bu": "060C",
      "stage": "2",
      "place": "ท่าเรือแหลมฉบัง Gate 3",
      "type": "ท่าเรือ",
      "start": "2026-01-28 14:00",
      "end": "2026-01-28 16:30",
      "duration": "2h 30m",
      "reason": "รอขึ้นสินค้า",
      "amount": 200.00,
      "status": "Approved",
      "statusColor": "Success"
    },
    {
      "id": "PRK-2026-0003",
      "shipment": "8062137301",
      "bu": "060E",
      "stage": "1",
      "place": "ลานจอดร่วมใจ โคราช",
      "type": "ลานจอดเอกชน",
      "start": "2026-01-29 12:00",
      "end": "2026-01-29 13:00",
      "duration": "1h 0m",
      "reason": "พักเที่ยง",
      "amount": 30.00,
      "status": "Pending Review",
      "statusColor": "Warning"
    },
    {
      "id": "PRK-2026-0004",
      "shipment": "8062137310",
      "bu": "060F",
      "stage": "1",
      "place": "คลังสินค้า บางตาพุด",
      "type": "คลังสินค้า",
      "start": "2026-01-30 09:00",
      "end": "2026-01-30 11:30",
      "duration": "2h 30m",
      "reason": "รอเอกสารศุลกากร",
      "amount": 0.00,
      "status": "Draft",
      "statusColor": "None"
    }
  ],
  "cashAdvances": [
    {
      "caNo": "CA-2026-0045",
      "employeeName": "นายศักดิ์ทิวาดล จินดาพิชัย",
      "employeeId": "39396",
      "type": "Driver Advance",
      "typeState": "Information",
      "bu": "060C",
      "caAmount": 5000,
      "disbursed": 5000,
      "expensed": 1500,
      "balance": 3500,
      "status": "Open",
      "daysOpen": 6,
      "warning": true
    },
    {
      "caNo": "CA-2026-0052",
      "employeeName": "นายสมชาย แสงทอง",
      "employeeId": "40125",
      "type": "Driver Advance",
      "typeState": "Information",
      "bu": "060E",
      "caAmount": 3000,
      "disbursed": 3000,
      "expensed": 300,
      "balance": 2700,
      "status": "Open",
      "daysOpen": 5,
      "warning": false
    },
    {
      "caNo": "CA-2026-0060",
      "employeeName": "นางสาวพิมพ์ใจ สุขสันต์",
      "employeeId": "50100",
      "type": "Site Advance",
      "typeState": "Success",
      "bu": "060C",
      "caAmount": 10000,
      "disbursed": 10000,
      "expensed": 3500,
      "balance": 6500,
      "status": "Open",
      "daysOpen": 4,
      "warning": false
    },
    {
      "caNo": "CA-2026-0070",
      "employeeName": "นายอนุชา ศิริสำเร็จ",
      "employeeId": "50200",
      "type": "Specific Advance",
      "typeState": "Warning",
      "bu": "060C",
      "caAmount": 8000,
      "disbursed": 8000,
      "expensed": 4200,
      "balance": 3800,
      "status": "Open",
      "daysOpen": 3,
      "warning": false
    }
  ],
  "recordedExpenses": [
    {
      "no": 1,
      "date": "2026-01-28 08:30",
      "refDoc": "RCP-10234",
      "employee": "นายศักดิ์ทิวาดล จินดาพิชัย",
      "type": "ค่าทางด่วน (Toll)",
      "group": "ค่าใช้จ่ายดำเนินงาน",
      "payType": "CASH",
      "amount": 250,
      "receipt": "📷",
      "status": "Approved",
      "statusState": "Success",
      "remark": ""
    },
    {
      "no": 2,
      "date": "2026-01-28 12:15",
      "refDoc": "-",
      "employee": "นายศักดิ์ทิวาดล จินดาพิชัย",
      "type": "ค่าอาหาร (Meal)",
      "group": "ค่าใช้จ่ายดำเนินงาน",
      "payType": "CASH",
      "amount": 150,
      "receipt": "-",
      "status": "Approved",
      "statusState": "Success",
      "remark": ""
    },
    {
      "no": 3,
      "date": "2026-01-28 17:00",
      "refDoc": "RCP-10236",
      "employee": "นายศักดิ์ทิวาดล จินดาพิชัย",
      "type": "ค่าน้ำหนัก (Weighbridge)",
      "group": "ค่าใช้จ่ายดำเนินงาน",
      "payType": "CASH",
      "amount": 100,
      "receipt": "📷",
      "status": "Approved",
      "statusState": "Success",
      "remark": ""
    },
    {
      "no": 4,
      "date": "2026-01-28 18:00",
      "refDoc": "RCP-10237",
      "employee": "นายศักดิ์ทิวาดล จินดาพิชัย",
      "type": "ค่าค้างคืน (Overnight)",
      "group": "ค่าใช้จ่ายดำเนินงาน",
      "payType": "CASH",
      "amount": 800,
      "receipt": "📷",
      "status": "Rejected",
      "statusState": "Error",
      "remark": "ใบเสร็จไม่ชัด กรุณาแนบใหม่"
    }
  ],
  "totalAmount": 1300,
   "fuelRecordss": [
      {
        "no": 1,
        "date": "2026-01-28 06:15",
        "fillType": "Fleet Card",
        "fillState": "Information",
        "slip": "FL-880123",
        "station": "PTT Station บางนา",
        "fuel": "Diesel B7",
        "liters": 180.50,
        "amount": 5584.67,
        "rate": "4.1 km/L",
        "status": "Approved",
        "statusState": "Success"
      },
      {
        "no": 2,
        "date": "2026-01-28 16:30",
        "fillType": "Cash",
        "fillState": "Success",
        "slip": "RCP-F-5501",
        "station": "Shell สระบุรี",
        "fuel": "Diesel B7",
        "liters": 50.00,
        "amount": 1547.00,
        "rate": "4.1 km/L",
        "status": "Approved",
        "statusState": "Success"
      }
    ],
    "totalLiters": 230.50,
    "TotalAmount": 7131.67,
     "fuelAllocation": [
      {
        "stage": 1,
        "from": "BPK",
        "fromDesc": "คลังสินค้า บางปะกง",
        "to": "C0001",
        "toDesc": "PTT Tank Terminal ระยอง",
        "startMiles": 100,
        "endMiles": 215,
        "distance": 115,
        "ratio": "44.4%",
        "fuel": 80.14,
        "cost": 2479.68
      },
      {
        "stage": 2,
        "from": "C0001",
        "fromDesc": "PTT Tank Terminal ระยอง",
        "to": "C0132",
        "toDesc": "คลังสินค้า อ่าวอุดม",
        "startMiles": 215,
        "endMiles": 301,
        "distance": 86,
        "ratio": "33.2%",
        "fuel": 59.93,
        "cost": 1854.37
      },
      {
        "stage": 3,
        "from": "C0132",
        "fromDesc": "คลังสินค้า อ่าวอุดม",
        "to": "C0001",
        "toDesc": "คลังสินค้า บางปะกง",
        "startMiles": 301,
        "endMiles": 359,
        "distance": 58,
        "ratio": "22.4%",
        "fuel": 40.42,
        "cost": 1250.62
      }
    ],
    "totalDistance": 259,
    "totalFuel": 180.50,
    "totalCost": 5584.67,
     "parkingRecordsTable": [
      {
        "no": 1,
        "stage": 1,
        "place": "ลานจอด PTT ระยอง",
        "type": "ปั๊มน้ำมัน",
        "start": "2026-01-28 10:30",
        "end": "2026-01-28 11:15",
        "duration": "0h 45m",
        "reason": "รอคิวถ่ายสินค้า",
        "amount": 50.00,
        "status": "Approved",
        "statusState": "Success"
      },
      {
        "no": 2,
        "stage": 2,
        "place": "ท่าเรือแหลมฉบัง Gate 3",
        "type": "ท่าเรือ",
        "start": "2026-01-28 14:00",
        "end": "2026-01-28 16:30",
        "duration": "2h 30m",
        "reason": "รอขึ้นสินค้า",
        "amount": 200.00,
        "status": "Approved",
        "statusState": "Success"
      }
    ],
    "Totalamount": 250.00,
     "consumptionRateMaster": [
      {
        "bu": "1400",
        "vehicle": "609400",
        "type": "10W",
        "brand": "ISUZU",
        "distanceRange": "1-400 km.",
        "rate": 4.1,
        "validFrom": "01.01.2020",
        "validTo": "31.12.9999"
      },
      {
        "bu": "1400",
        "vehicle": "609401",
        "type": "10W",
        "brand": "ISUZU",
        "distanceRange": "1-400 km.",
        "rate": 3.3,
        "validFrom": "01.01.2020",
        "validTo": "31.12.9999"
      },
      {
        "bu": "1400",
        "vehicle": "609401",
        "type": "10W",
        "brand": "ISUZU",
        "distanceRange": "401 km. ขึ้นไป",
        "rate": 3.6,
        "validFrom": "01.01.2020",
        "validTo": "31.12.9999"
      },
      {
        "bu": "1400",
        "vehicle": "610053",
        "type": "10W",
        "brand": "ISUZU",
        "distanceRange": "1-400 km.",
        "rate": 3.3,
        "validFrom": "01.01.2020",
        "validTo": "31.12.9999"
      },
      {
        "bu": "060X",
        "vehicle": "653712",
        "type": "10W",
        "brand": "ISUZU",
        "distanceRange": "1-9999",
        "rate": 4.7,
        "validFrom": "01.01.2020",
        "validTo": "31.12.9999"
      }
    ]

}
